AsyncLibrary/__init__.py
AsyncLibrary/_version.py
AsyncLibrary/protected_ordered_dict.py
AsyncLibrary/robot_async.py
AsyncLibrary/scoped_value.py
robotframework_async_keyword-1.1.15.dist-info/LICENSE.txt
robotframework_async_keyword-1.1.15.dist-info/METADATA
robotframework_async_keyword-1.1.15.dist-info/WHEEL
robotframework_async_keyword-1.1.15.dist-info/top_level.txt
robotframework_async_keyword-1.1.15.dist-info/RECORD
