Metadata-Version: 2.2
Name: robotframework-async-keyword
Version: 1.1.15
Summary: Generic Robot Framework library for asynchronous keyword execution
Author-email: René Lehfeld <54720674+rlehfeld@users.noreply.github.com>
License: MIT
Project-URL: Homepage, https://github.com/rlehfeld/robotframework-async-keyword
Project-URL: Bug Reports, https://github.com/rlehfeld/robotframework-async-keyword/issues
Project-URL: Source, https://github.com/rlehfeld/robotframework-async-keyword/
Keywords: async,robotframework
Classifier: Programming Language :: Python :: 3
Classifier: Environment :: Other Environment
Classifier: Intended Audience :: Developers
Classifier: Operating System :: OS Independent
Classifier: Topic :: Software Development :: Libraries :: Python Modules
Obsoletes: robotframework_async
Requires-Python: >=3.7
License-File: LICENSE.txt
Requires-Dist: robotframework>=5.0.1
